relenv/__init__.py
relenv/__main__.py
relenv/buildenv.py
relenv/check.py
relenv/common.py
relenv/create.py
relenv/fetch.py
relenv/manifest.py
relenv/python-versions.json
relenv/pyversions.py
relenv/relocate.py
relenv/runtime.py
relenv/toolchain.py
relenv/_resources/xz/config.h
relenv/_resources/xz/readme.md
relenv/_scripts/install_vc_build.ps1
relenv/build/__init__.py
relenv/build/darwin.py
relenv/build/linux.py
relenv/build/windows.py
relenv/build/common/__init__.py
relenv/build/common/_sysconfigdata_template.py
relenv/build/common/builder.py
relenv/build/common/builders.py
relenv/build/common/download.py
relenv/build/common/install.py
relenv/build/common/ui.py
relenv-0.22.2.dist-info/licenses/LICENSE.md
relenv-0.22.2.dist-info/licenses/NOTICE
tests/__init__.py
tests/_pytest_typing.py
tests/conftest.py
tests/test_build.py
tests/test_common.py
tests/test_create.py
tests/test_downloads.py
tests/test_fips_photon.py
tests/test_module_imports.py
tests/test_pyversions_runtime.py
tests/test_relocate.py
tests/test_relocate_module.py
tests/test_runtime.py
tests/test_verify_build.py
relenv-0.22.2.dist-info/METADATA
relenv-0.22.2.dist-info/WHEEL
relenv-0.22.2.dist-info/entry_points.txt
relenv-0.22.2.dist-info/top_level.txt
relenv-0.22.2.dist-info/RECORD
