Metadata-Version: 2.4
Name: relenv
Version: 0.22.2
Project-URL: Source Code, https://github.com/saltstack/relative-environment-for-python
Project-URL: Documentation, https://relenv.readthedocs.io/en/latest/
Project-URL: Changelog, https://relenv.readthedocs.io/en/latest/changelog.html
License-File: LICENSE.md
License-File: NOTICE
Provides-Extra: toolchain
Requires-Dist: ppbt; extra == "toolchain"
Dynamic: license-file
